ccframe/__init__.py
ccframe/api.py
ccframe/middleware.py
ccframe/response.py
ccframe-0.0.2.dist-info/METADATA
ccframe-0.0.2.dist-info/WHEEL
ccframe-0.0.2.dist-info/top_level.txt
ccframe-0.0.2.dist-info/RECORD
