Metadata-Version: 2.1
Name: ccframe
Version: 0.0.2
Summary: ccframe - simple web framework. Cloned from Bumbo Python Web Framework course
Home-page: UNKNOWN
Author: Alex Shanin
Author-email: shanin.x@gmail.com
License: MIT
Platform: UNKNOWN
Classifier: Programming Language :: Python :: 3.6
Requires-Python: >=3.6.0
Requires-Dist: Jinja2 (==2.11.2)
Requires-Dist: WebOb (==1.8.6)
Requires-Dist: parse (==1.15.0)
Requires-Dist: requests-wsgi-adapter (==0.4.1)
Requires-Dist: requests (==2.24.0)
Requires-Dist: whitenoise (==5.1.0)
